AUTHORS
COPYING_GPL
ChangeLog
MANIFEST.in
README
build.py
eggsetup.py
setup.py
docs/introduction.html
docs/introduction.rst
docs/running_perftest.txt
docs/api/api-objects.txt
docs/api/class-tree.html
docs/api/crarr.png
docs/api/epydoc.css
docs/api/epydoc.js
docs/api/frames.html
docs/api/help.html
docs/api/identifier-index.html
docs/api/index.html
docs/api/module-tree.html
docs/api/redirect.html
docs/api/toc-everything.html
docs/api/toc-xappy-module.html
docs/api/toc-xappy._checkxapian-module.html
docs/api/toc-xappy.datastructures-module.html
docs/api/toc-xappy.errors-module.html
docs/api/toc-xappy.fieldactions-module.html
docs/api/toc-xappy.fieldmappings-module.html
docs/api/toc-xappy.highlight-module.html
docs/api/toc-xappy.indexerconnection-module.html
docs/api/toc-xappy.marshall-module.html
docs/api/toc-xappy.memutils-module.html
docs/api/toc-xappy.parsedate-module.html
docs/api/toc-xappy.replaylog-module.html
docs/api/toc-xappy.schema-module.html
docs/api/toc-xappy.searchconnection-module.html
docs/api/toc.html
docs/api/xappy-module.html
docs/api/xappy-pysrc.html
docs/api/xappy._checkxapian-module.html
docs/api/xappy._checkxapian-pysrc.html
docs/api/xappy.datastructures-module.html
docs/api/xappy.datastructures-pysrc.html
docs/api/xappy.datastructures.Field-class.html
docs/api/xappy.datastructures.ProcessedDocument-class.html
docs/api/xappy.datastructures.UnprocessedDocument-class.html
docs/api/xappy.errors-module.html
docs/api/xappy.errors-pysrc.html
docs/api/xappy.errors.IndexerError-class.html
docs/api/xappy.errors.SearchEngineError-class.html
docs/api/xappy.errors.SearchError-class.html
docs/api/xappy.errors.XapianError-class.html
docs/api/xappy.fieldactions-module.html
docs/api/xappy.fieldactions-pysrc.html
docs/api/xappy.fieldactions.ActionContext-class.html
docs/api/xappy.fieldactions.FieldActions-class.html
docs/api/xappy.fieldactions.SortableMarshaller-class.html
docs/api/xappy.fieldmappings-module.html
docs/api/xappy.fieldmappings-pysrc.html
xappy.egg-info/PKG-INFO
xappy.egg-info/SOURCES.txt
xappy.egg-info/dependency_links.txt
xappy.egg-info/top_level.txt