Metadata-Version: 1.0
Name: xappy
Version: 0.5
Summary: Easy-to-use interface to the Xapian search engine
Home-page: http://code.google.com/p/xappy
Author: Richard Boulton
Author-email: richard@lemurconsulting.com
License: GPL
Download-URL: http://xappy.googlecode.com/files/xappy-0.5.tar.gz
Platform: Any
Classifier: Development Status :: 3 - Alpha
Classifier: Intended Audience :: Developers
Classifier: License :: OSI Approved :: GNU General Public License (GPL)
Classifier: Programming Language :: C++
Classifier: Topic :: Internet :: WWW/HTTP :: Indexing/Search
Classifier: Operating System :: MacOS
Classifier: Operating System :: Microsoft
Classifier: Operating System :: POSIX
